integration/__init__.py
integration/helpers.py
integration/test_sen1_native.py
integration/test_sen2_analysis.py
integration/test_sen2_native.py
integration/test_sen3_analysis.py
integration/test_sen3_native.py
tests/amodes/__init__.py
tests/amodes/test_sentinel1.py
tests/amodes/test_sentinel2.py
tests/amodes/test_sentinel3.py
tests/helpers/__init__.py
tests/helpers/sentinel2.py
tests/helpers/sentinel3.py
xarray_eopf/__init__.py
xarray_eopf/amode.py
xarray_eopf/backend.py
xarray_eopf/coarsen.py
xarray_eopf/constants.py
xarray_eopf/filter.py
xarray_eopf/flatten.py
xarray_eopf/prefix.py
xarray_eopf/source.py
xarray_eopf/utils.py
xarray_eopf/version.py
xarray_eopf/amodes/__init__.py
xarray_eopf/amodes/sentinel1.py
xarray_eopf/amodes/sentinel2.py
xarray_eopf/amodes/sentinel3.py
xarray_eopf-0.2.4.dist-info/licenses/LICENSE
xarray_eopf-0.2.4.dist-info/METADATA
xarray_eopf-0.2.4.dist-info/WHEEL
xarray_eopf-0.2.4.dist-info/entry_points.txt
xarray_eopf-0.2.4.dist-info/top_level.txt
xarray_eopf-0.2.4.dist-info/RECORD
