Metadata-Version: 2.4
Name: xarray-eopf
Version: 0.2.4
Summary: A backend implmentation for xarray that allows for analysis-ready reading of ESA EOPF data products.
Author: Konstantin Ntokas (Brockmann Consult GmbH), Norman Fomferra (Brockmann Consult GmbH)
License: Apache-2.0
Project-URL: Documentation, https://eopf-sample-service.github.io/xarray-eopf
Project-URL: Repository, https://github.com/EOPF-Sample-Service/xarray-eopf
Project-URL: Changelog, https://github.com/EOPF-Sample-Service/xarray-eopf/blob/main/CHANGES.md
Project-URL: Issues, https://github.com/EOPF-Sample-Service/xarray-eopf/issues
Keywords: copernicus,esa,eopf,sentinel,xarray,zarr
Classifier: Development Status :: 5 - Production/Stable
Classifier: Intended Audience :: Science/Research
Classifier: Intended Audience :: Developers
Classifier: License :: OSI Approved :: Apache Software License
Classifier: Programming Language :: Python :: 3
Classifier: Programming Language :: Python :: 3.10
Classifier: Programming Language :: Python :: 3.11
Classifier: Programming Language :: Python :: 3.12
Classifier: Programming Language :: Python :: 3.13
Classifier: Topic :: Software Development
Classifier: Topic :: Scientific/Engineering
Classifier: Typing :: Typed
Classifier: Operating System :: Microsoft :: Windows
Classifier: Operating System :: POSIX
Classifier: Operating System :: Unix
Classifier: Operating System :: MacOS
Requires-Python: >=3.10
License-File: LICENSE
Requires-Dist: affine>=2.2
Requires-Dist: aiohttp
Requires-Dist: dask
Requires-Dist: dask-image
Requires-Dist: fsspec
Requires-Dist: numba
Requires-Dist: numpy
Requires-Dist: pyproj
Requires-Dist: requests
Requires-Dist: s3fs
Requires-Dist: xarray>=2024.10
Requires-Dist: xcube-resampling>=0.2.0
Requires-Dist: zarr<3.0,>=2
Provides-Extra: dev
Requires-Dist: build; extra == "dev"
Requires-Dist: hatch; extra == "dev"
Requires-Dist: twine; extra == "dev"
Requires-Dist: black; extra == "dev"
Requires-Dist: isort; extra == "dev"
Requires-Dist: ruff; extra == "dev"
Requires-Dist: pytest; extra == "dev"
Requires-Dist: pytest-cov; extra == "dev"
Requires-Dist: jupyterlab; extra == "dev"
Requires-Dist: matplotlib; extra == "dev"
Provides-Extra: doc
Requires-Dist: mkdocs; extra == "doc"
Requires-Dist: mkdocs-autorefs; extra == "doc"
Requires-Dist: mkdocs-material; extra == "doc"
Requires-Dist: mkdocstrings; extra == "doc"
Requires-Dist: mkdocstrings-python; extra == "doc"
Dynamic: license-file
